open_source_library_data_collector-1.1.0.dist-info/DESCRIPTION.rst
open_source_library_data_collector-1.1.0.dist-info/METADATA
open_source_library_data_collector-1.1.0.dist-info/metadata.json
open_source_library_data_collector-1.1.0.dist-info/RECORD
open_source_library_data_collector-1.1.0.dist-info/top_level.txt
open_source_library_data_collector-1.1.0.dist-info/WHEEL
test/__init__.py
test/test.py
