Metadata-Version: 2.0
Name: open-source-library-data-collector
Version: 1.1.0
Summary: Periodically capture external data relating to GitHub hosted Open Source libraries
Home-page: https://github.com/sendgrid/open-source-library-data-collector
Author: Elmer Thomas
Author-email: dx@sendgrid.com
License: MIT
Keywords: GitHub,Open Source,ROI,Reporting,Package Managers
Platform: UNKNOWN
Classifier: Programming Language :: Python :: 3.2
Classifier: Programming Language :: Python :: 3.3
Classifier: Programming Language :: Python :: 3.4
Classifier: Programming Language :: Python :: 3.5
Requires-Dist: github3.py
Requires-Dist: requests
Requires-Dist: beautifulsoup4
Requires-Dist: sendgrid
Requires-Dist: python-dateutil
Requires-Dist: sqlalchemy
Requires-Dist: datetime
Requires-Dist: pyyaml
Requires-Dist: six
Requires-Dist: wheel
Requires-Dist: zope.interface
Requires-Dist: uritemplate
Requires-Dist: uritemplate.py
Requires-Dist: pytz
Requires-Dist: python-http-client
